MaxText/__init__.py
MaxText/accelerator_to_spec_map.py
MaxText/benchmark_chunked_prefill.py
MaxText/checkpointing.py
MaxText/common_types.py
MaxText/convert_deepseek_family_ckpt.py
MaxText/convert_deepseek_family_unscanned_ckpt.py
MaxText/convert_gemma2_chkpt.py
MaxText/convert_gemma3_chkpt.py
MaxText/convert_gemma_chkpt.py
MaxText/convert_gpt3_ckpt_from_paxml.py
MaxText/convert_gpt_oss_ckpt.py
MaxText/convert_gpt_oss_unscanned_ckpt.py
MaxText/convert_qwen3_moe.py
MaxText/data_loader.py
MaxText/decode.py
MaxText/deepseek_fp8_to_bf16.py
MaxText/dpo_utils.py
MaxText/elastic_train.py
MaxText/exceptions.py
MaxText/gcp_workload_monitor.py
MaxText/generate_distillation_data.py
MaxText/generate_param_only_checkpoint.py
MaxText/get_flops.py
MaxText/globals.py
MaxText/inference_microbenchmark.py
MaxText/inference_microbenchmark_sweep.py
MaxText/inference_utils.py
MaxText/layerwise_quantization.py
MaxText/llama4_ckpt_unscanned.py
MaxText/llama_ckpt_conversion_inference_only.py
MaxText/llama_mistral_mixtral_orbax_to_hf.py
MaxText/llama_or_mistral_ckpt.py
MaxText/load_and_quantize_checkpoint.py
MaxText/max_logging.py
MaxText/max_utils.py
MaxText/maxengine.py
MaxText/maxengine_config.py
MaxText/maxengine_server.py
MaxText/maxtext_utils.py
MaxText/metric_logger.py
MaxText/model_creation_utils.py
MaxText/multihost_dataloading.py
MaxText/multimodal_utils.py
MaxText/optimizers.py
MaxText/prefill_packing.py
MaxText/profiler.py
MaxText/pyconfig.py
MaxText/sequence_packing.py
MaxText/sft_trainer.py
MaxText/standalone_checkpointer.py
MaxText/standalone_dataloader.py
MaxText/tokenizer.py
MaxText/train.py
MaxText/train_compile.py
MaxText/train_tokenizer.py
MaxText/train_utils.py
MaxText/vertex_tensorboard.py
MaxText/weight_inspector.py
MaxText/assets/tokenizer
MaxText/assets/tokenizer.gemma
MaxText/assets/tokenizer.gemma3
MaxText/assets/tokenizer.llama2
MaxText/assets/tokenizer.mistral-v1
MaxText/assets/tokenizer.mistral-v3
MaxText/assets/tokenizer_llama3.tiktoken
maxtext-0.1.0.dist-info/METADATA
maxtext-0.1.0.dist-info/WHEEL
maxtext-0.1.0.dist-info/entry_points.txt
maxtext-0.1.0.dist-info/licenses/AUTHORS
maxtext-0.1.0.dist-info/licenses/LICENSE
maxtext-0.1.0.dist-info/RECORD
