Metadata-Version: 2.4
Name: maxtext
Version: 0.1.0
Summary: MaxText is a simple, performant and scalable Jax LLM!
Project-URL: Repository, https://github.com/AI-Hypercomputer/maxtext.git
Project-URL: Bug Tracker, https://github.com/AI-Hypercomputer/maxtext/issues
License-Expression: Apache-2.0
License-File: AUTHORS
License-File: LICENSE
Keywords: deepseek,gemma,jax,llama,llm,mistral,mixtral
Classifier: Development Status :: 4 - Beta
Classifier: Environment :: GPU
Classifier: Programming Language :: ML
Classifier: Programming Language :: Python
Classifier: Programming Language :: Python :: 3.12
Requires-Python: >=3.12
Requires-Dist: absl-py>=2.3.1
Requires-Dist: aiofiles>=24.1.0
Requires-Dist: aiohappyeyeballs>=2.6.1
Requires-Dist: aiohttp>=3.12.15
Requires-Dist: aiosignal>=1.4.0
Requires-Dist: annotated-types>=0.7.0
Requires-Dist: antlr4-python3-runtime>=4.9.3
Requires-Dist: anyio>=4.10.0
Requires-Dist: aqtp>=0.9.0
Requires-Dist: array-record>=0.8.1
Requires-Dist: astroid>=3.3.11
Requires-Dist: astunparse>=1.6.3
Requires-Dist: attrs>=25.3.0
Requires-Dist: auditwheel>=6.4.1
Requires-Dist: black>=24.10.0
Requires-Dist: blobfile>=3.1.0
Requires-Dist: build>=1.2.2.post1
Requires-Dist: cachetools>=5.5.2
Requires-Dist: certifi>=2025.8.3
Requires-Dist: cffi>=1.17.1; platform_python_implementation == 'PyPy'
Requires-Dist: cfgv>=3.4.0
Requires-Dist: charset-normalizer>=3.4.3
Requires-Dist: chex>=0.1.90
Requires-Dist: click>=8.2.1
Requires-Dist: cloud-accelerator-diagnostics>=0.1.1
Requires-Dist: cloud-tpu-diagnostics>=0.1.5
Requires-Dist: cloudpickle>=3.1.1
Requires-Dist: clu>=0.0.12
Requires-Dist: colorama>=0.4.6
Requires-Dist: contourpy>=1.3.2
Requires-Dist: coverage>=7.10.6
Requires-Dist: cycler>=0.12.1
Requires-Dist: decorator>=5.2.1
Requires-Dist: dill>=0.3.8
Requires-Dist: distlib>=0.4.0
Requires-Dist: dm-tree>=0.1.9
Requires-Dist: docstring-parser>=0.17.0
Requires-Dist: editdistance>=0.8.1
Requires-Dist: einops>=0.8.1
Requires-Dist: etils>=1.13.0
Requires-Dist: evaluate>=0.4.5
Requires-Dist: execnet>=2.1.1
Requires-Dist: fastapi>=0.116.1
Requires-Dist: filelock>=3.18.0
Requires-Dist: flatbuffers>=25.2.10
Requires-Dist: flax>=0.11.2
Requires-Dist: fonttools>=4.59.0
Requires-Dist: frozenlist>=1.7.0
Requires-Dist: fsspec>=2025.7.0
Requires-Dist: gast>=0.6.0
Requires-Dist: gcsfs>=2025.7.0
Requires-Dist: google-api-core>=2.25.1
Requires-Dist: google-api-python-client>=2.181.0
Requires-Dist: google-auth-httplib2>=0.2.0
Requires-Dist: google-auth-oauthlib>=1.2.2
Requires-Dist: google-auth>=2.40.3
Requires-Dist: google-cloud-aiplatform>=1.111.0
Requires-Dist: google-cloud-appengine-logging>=1.6.2
Requires-Dist: google-cloud-audit-log>=0.3.2
Requires-Dist: google-cloud-bigquery>=3.36.0
Requires-Dist: google-cloud-core>=2.4.3
Requires-Dist: google-cloud-logging>=3.12.1
Requires-Dist: google-cloud-monitoring>=2.27.2
Requires-Dist: google-cloud-resource-manager>=1.14.2
Requires-Dist: google-cloud-storage>=2.19.0
Requires-Dist: google-crc32c>=1.7.1
Requires-Dist: google-genai>=1.33.0
Requires-Dist: google-pasta>=0.2.0
Requires-Dist: google-resumable-media>=2.7.2
Requires-Dist: googleapis-common-protos>=1.70.0
Requires-Dist: grain>=0.2.12
Requires-Dist: grpc-google-iam-v1>=0.14.2
Requires-Dist: grpcio-status>=1.71.2
Requires-Dist: grpcio>=1.74.0
Requires-Dist: gviz-api>=1.10.0
Requires-Dist: h11>=0.16.0
Requires-Dist: h5py>=3.14.0
Requires-Dist: hf-xet>=1.1.9; platform_machine == 'aarch64' or platform_machine == 'amd64' or platform_machine == 'arm64' or platform_machine == 'x86_64'
Requires-Dist: httpcore>=1.0.9
Requires-Dist: httplib2>=0.30.0
Requires-Dist: httpx>=0.28.1
Requires-Dist: huggingface-hub>=0.34.4
Requires-Dist: humanize>=4.13.0
Requires-Dist: hypothesis>=6.136.4
Requires-Dist: identify>=2.6.14
Requires-Dist: idna>=3.10
Requires-Dist: immutabledict>=4.2.1
Requires-Dist: importlab>=0.8.1
Requires-Dist: importlib-metadata>=8.7.0
Requires-Dist: importlib-resources>=6.5.2
Requires-Dist: iniconfig>=2.1.0
Requires-Dist: isort>=6.0.1
Requires-Dist: jax>=0.7.0
Requires-Dist: jaxlib>=0.7.0
Requires-Dist: jaxtyping>=0.3.2
Requires-Dist: jinja2>=3.1.6
Requires-Dist: joblib>=1.5.2
Requires-Dist: jsonlines>=4.0.0
Requires-Dist: keras>=3.11.3
Requires-Dist: kiwisolver>=1.4.8
Requires-Dist: libclang>=18.1.1
Requires-Dist: libcst>=1.8.2
Requires-Dist: libtpu>=0.0.19; platform_machine == 'x86_64' and sys_platform == 'linux'
Requires-Dist: lxml>=6.0.1
Requires-Dist: markdown-it-py>=3.0.0
Requires-Dist: markdown>=3.9
Requires-Dist: markupsafe>=3.0.2
Requires-Dist: matplotlib>=3.10.3
Requires-Dist: mccabe>=0.7.0
Requires-Dist: mdurl>=0.1.2
Requires-Dist: ml-collections>=1.1.0
Requires-Dist: ml-dtypes>=0.5.3
Requires-Dist: ml-goodput-measurement>=0.0.14
Requires-Dist: more-itertools>=10.8.0
Requires-Dist: mpmath>=1.3.0
Requires-Dist: msgpack>=1.1.1
Requires-Dist: msgspec>=0.19.0
Requires-Dist: multidict>=6.6.4
Requires-Dist: multiprocess>=0.70.16
Requires-Dist: mypy-extensions>=1.1.0
Requires-Dist: namex>=0.1.0
Requires-Dist: nest-asyncio>=1.6.0
Requires-Dist: networkx>=3.5
Requires-Dist: ninja>=1.13.0
Requires-Dist: nltk>=3.9.1
Requires-Dist: nodeenv>=1.9.1
Requires-Dist: numpy>=2.0.2
Requires-Dist: oauthlib>=3.3.1
Requires-Dist: omegaconf>=2.3.0
Requires-Dist: opentelemetry-api>=1.36.0
Requires-Dist: opt-einsum>=3.4.0
Requires-Dist: optax>=0.2.5
Requires-Dist: optree>=0.17.0
Requires-Dist: orbax-checkpoint>=0.11.24
Requires-Dist: packaging>=25.0
Requires-Dist: pandas>=2.3.2
Requires-Dist: parameterized>=0.9.0
Requires-Dist: pathspec>=0.12.1
Requires-Dist: pathwaysutils>=0.1.2
Requires-Dist: pillow>=11.3.0
Requires-Dist: platformdirs>=4.4.0
Requires-Dist: pluggy>=1.6.0
Requires-Dist: portpicker>=1.6.0
Requires-Dist: pre-commit>=4.3.0
Requires-Dist: prometheus-client>=0.22.1
Requires-Dist: promise>=2.3
Requires-Dist: propcache>=0.3.2
Requires-Dist: proto-plus>=1.26.1
Requires-Dist: protobuf>=5.29.5
Requires-Dist: psutil>=7.0.0
Requires-Dist: pyarrow>=21.0.0
Requires-Dist: pyasn1-modules>=0.4.2
Requires-Dist: pyasn1>=0.6.1
Requires-Dist: pycnite>=2024.7.31
Requires-Dist: pycparser>=2.22; platform_python_implementation == 'PyPy'
Requires-Dist: pycryptodomex>=3.23.0
Requires-Dist: pydantic-core>=2.33.2
Requires-Dist: pydantic>=2.11.7
Requires-Dist: pydot>=4.0.1
Requires-Dist: pyelftools>=0.32
Requires-Dist: pyglove>=0.4.5
Requires-Dist: pygments>=2.19.2
Requires-Dist: pyink>=24.10.1
Requires-Dist: pylint>=3.3.8
Requires-Dist: pyparsing>=3.2.3
Requires-Dist: pyproject-hooks>=1.2.0
Requires-Dist: pytest-xdist>=3.8.0
Requires-Dist: pytest>=8.4.1
Requires-Dist: python-dateutil>=2.9.0.post0
Requires-Dist: pytype>=2024.10.11
Requires-Dist: pytz>=2025.2
Requires-Dist: pyyaml>=6.0.2
Requires-Dist: regex>=2025.9.1
Requires-Dist: requests-oauthlib>=2.0.0
Requires-Dist: requests>=2.32.5
Requires-Dist: rich>=14.1.0
Requires-Dist: rsa>=4.9.1
Requires-Dist: safetensors>=0.6.2
Requires-Dist: scipy>=1.16.0
Requires-Dist: sentencepiece>=0.2.1
Requires-Dist: seqio>=0.0.20
Requires-Dist: setuptools>=80.9.0
Requires-Dist: shapely>=2.1.1
Requires-Dist: shortuuid>=1.0.13
Requires-Dist: simple-parsing>=0.1.7
Requires-Dist: simplejson>=3.20.1
Requires-Dist: six>=1.17.0
Requires-Dist: sniffio>=1.3.1
Requires-Dist: sortedcontainers>=2.4.0
Requires-Dist: starlette>=0.47.3
Requires-Dist: sympy>=1.14.0
Requires-Dist: tabulate>=0.9.0
Requires-Dist: tenacity>=9.1.2
Requires-Dist: tensorboard-data-server>=0.7.2
Requires-Dist: tensorboard-plugin-profile>=2.13.0
Requires-Dist: tensorboard>=2.19.0
Requires-Dist: tensorboardx>=2.6.4
Requires-Dist: tensorflow-datasets>=4.9.9
Requires-Dist: tensorflow-metadata>=1.17.2
Requires-Dist: tensorflow-text>=2.19.0
Requires-Dist: tensorflow>=2.19.1
Requires-Dist: tensorstore>=0.1.76
Requires-Dist: termcolor>=3.1.0
Requires-Dist: tiktoken>=0.11.0
Requires-Dist: tokenizers>=0.22.0
Requires-Dist: toml>=0.10.2
Requires-Dist: tomlkit>=0.13.3
Requires-Dist: toolz>=1.0.0
Requires-Dist: tqdm>=4.67.1
Requires-Dist: transformers>=4.56.1
Requires-Dist: treescope>=0.1.10
Requires-Dist: typing-extensions>=4.14.1
Requires-Dist: typing-inspection>=0.4.1
Requires-Dist: tzdata>=2025.2
Requires-Dist: uritemplate>=4.2.0
Requires-Dist: urllib3>=2.5.0
Requires-Dist: uvicorn>=0.35.0
Requires-Dist: virtualenv>=20.34.0
Requires-Dist: wadler-lindig>=0.1.7
Requires-Dist: websockets>=15.0.1
Requires-Dist: werkzeug>=3.1.3
Requires-Dist: wheel>=0.45.1
Requires-Dist: wrapt>=1.17.3
Requires-Dist: xxhash>=3.5.0
Requires-Dist: yarl>=1.20.1
Requires-Dist: zipp>=3.23.0
Requires-Dist: zstandard>=0.23.0
